<Properties StartupConfiguration="{2D594426-E737-41EB-A519-D905BD452956}|https">
  <MonoDevelop.Ide.ItemProperties.Presentation PreferredExecutionTarget="/Applications/Google Chrome.app" />
  <MonoDevelop.Ide.DebuggingService.PinnedWatches />
  <MonoDevelop.Ide.DebuggingService.Breakpoints>
    <BreakpointStore />
  </MonoDevelop.Ide.DebuggingService.Breakpoints>
  <MonoDevelop.Ide.Workbench>
    <Pads>
      <Pad Id="ProjectPad">
        <State name="__root__">
          <Node name="MVCFinalProject" expanded="True">
            <Node name="Business" expanded="True">
              <Node name="Services" expanded="True">
                <Node name="Admin" expanded="True">
                  <Node name="Abstract" expanded="True" />
                  <Node name="Concrete" expanded="True" />
                </Node>
              </Node>
              <Node name="ViewModels" expanded="True">
                <Node name="Admin" expanded="True">
                  <Node name="Account" expanded="True" />
                  <Node name="Slider" expanded="True" />
                </Node>
                <Node name="User" expanded="True">
                  <Node name="Account" expanded="True" />
                </Node>
              </Node>
            </Node>
            <Node name="Common" expanded="True">
              <Node name="Constants" expanded="True" />
              <Node name="Entities" expanded="True">
                <Node name="Base" expanded="True" />
              </Node>
            </Node>
            <Node name="DataAccess" expanded="True">
              <Node name="Contexts" expanded="True" />
              <Node name="Repositories" expanded="True">
                <Node name="Abstract" expanded="True" />
                <Node name="Base" expanded="True" />
                <Node name="Concrete" expanded="True" />
              </Node>
            </Node>
            <Node name="Presentation" expanded="True" />
          </Node>
        </State>
      </Pad>
    </Pads>
  </MonoDevelop.Ide.Workbench>
  <MultiItemStartupConfigurations />
  <MonoDevelop.Ide.Workspace ActiveConfiguration="Debug" />
</Properties>